pyfo
