Metadata-Version: 1.0
Name: pyfo
Version: 0.6
Summary: Easily generate XML from Python data structures.
Home-page: http://foss.cpcc.edu/pyfo/
Author: Luke Arno
Author-email: luke.arno@gmail.com
License: LGPL
Keywords: xml html
Platform: UNKNOWN
Classifier: Development Status :: 3 - Alpha
Classifier: Intended Audience :: Developers
Classifier: License :: OSI Approved :: GNU Library or Lesser General Public License (LGPL)
Classifier: Natural Language :: English
Classifier: Operating System :: OS Independent
Classifier: Programming Language :: Python
Classifier: Topic :: Software Development :: Libraries
Classifier: Topic :: Text Processing :: Markup :: XML
Classifier: Topic :: Text Processing :: Markup :: HTML
Classifier: Topic :: Utilities
